villog/__init__.py
villog/log.py
villog/mail_man.py
villog/mssql.py
villog/pdf.py
villog/readexcel.py
villog/writexcel.py
villog-0.3.4.dist-info/licenses/LICENSE
villog-0.3.4.dist-info/METADATA
villog-0.3.4.dist-info/WHEEL
villog-0.3.4.dist-info/top_level.txt
villog-0.3.4.dist-info/RECORD
